ckanext_visualize-1.0.0-py3.8-nspkg.pth
ckanext/visualize/__init__.py
ckanext/visualize/default_color_palette.py
ckanext/visualize/helpers.py
ckanext/visualize/plugin.py
ckanext/visualize/assets/webassets.yml
ckanext/visualize/assets/css/data_viewer.css
ckanext/visualize/assets/css/hide_preview_button.css
ckanext/visualize/assets/css/visualize_main.css
ckanext/visualize/assets/js/modules/visualize-chart-icon-reset.js
ckanext/visualize/assets/js/modules/visualize-chart-type.js
ckanext/visualize/assets/js/modules/visualize-colors-settings-add.js
ckanext/visualize/assets/js/modules/visualize-colors-settings-remove.js
ckanext/visualize/assets/js/modules/visualize-colors-settings-reset.js
ckanext/visualize/assets/js/modules/visualize-data.js
ckanext/visualize/assets/js/vendor/backend.ckan.js
ckanext/visualize/assets/js/vendor/chart.bundle.js
ckanext/visualize/assets/js/vendor/sortable.js
ckanext/visualize/public/base/images/Bar-symbol.png
ckanext/visualize/public/base/images/Chart-placeholder.png
ckanext/visualize/public/base/images/Line-symbol.png
ckanext/visualize/public/base/images/No-chart-illustration.png
ckanext/visualize/public/base/images/Point-symbol.png
ckanext/visualize/templates/base.html
ckanext/visualize/templates/visualize_form.html
ckanext/visualize/templates/visualize_view.html
ckanext/visualize/templates/admin/base.html
ckanext/visualize/templates/admin/visualize_data.html
ckanext/visualize/templates/package/view_edit_base.html
ckanext/visualize/templates/snippets/visualize_view_show.html
ckanext/visualize/templates/visualize/data_viewer.html
ckanext/visualize/tests/__init__.py
ckanext/visualize/tests/test_blueprints.py
ckanext/visualize/tests/test_helpers.py
ckanext/visualize/tests/test_view.py
ckanext/visualize/views/__init__.py
ckanext/visualize/views/admin_visualize.py
ckanext/visualize/views/visualize.py
ckanext_visualize-1.0.0.dist-info/LICENSE
ckanext_visualize-1.0.0.dist-info/METADATA
ckanext_visualize-1.0.0.dist-info/NOTICE
ckanext_visualize-1.0.0.dist-info/WHEEL
ckanext_visualize-1.0.0.dist-info/entry_points.txt
ckanext_visualize-1.0.0.dist-info/namespace_packages.txt
ckanext_visualize-1.0.0.dist-info/top_level.txt
ckanext_visualize-1.0.0.dist-info/RECORD
