Metadata-Version: 2.1
Name: ckanext-visualize
Version: 1.0.0
Summary: Visualize tabular data in CKAN
Home-page: https://github.com/keitaroinc/ckanext-visualize
Author: Keitaro Inc
Author-email: info@keitaro.com
License: MIT
Keywords: CKAN data chart visualize
Platform: UNKNOWN
Classifier: Development Status :: 5 - Production/Stable
Classifier: License :: OSI Approved :: MIT License
Classifier: Programming Language :: Python :: 3.8
Requires-Dist: natsort (==7.1.1)
